ogialibs/__init__.py
ogialibs/data.py
ogialibs-0.3.2.dist-info/METADATA
ogialibs-0.3.2.dist-info/WHEEL
ogialibs-0.3.2.dist-info/top_level.txt
ogialibs-0.3.2.dist-info/RECORD
