Metadata-Version: 2.1
Name: ogialibs
Version: 0.3.2
Summary: Common Python methods for OGIA
Project-URL: Homepage, https://github.com/Office-of-Groundwater-Impact-Assessment/ogialibs
Project-URL: Issues, https://github.com/Office-of-Groundwater-Impact-Assessment/ogialibs/issues
Classifier: Programming Language :: Python :: 3
Classifier: Operating System :: OS Independent
Requires-Python: >=3.8
